tabsynth/__init__.py
tabsynth/candidates.py
tabsynth/cli.py
tabsynth/cost.py
tabsynth/fretboard.py
tabsynth/model.py
tabsynth/optimize.py
tabsynth/pipeline.py
tabsynth/render.py
tabsynth/templates.py
tabsynth-1.0.6.dist-info/METADATA
tabsynth-1.0.6.dist-info/WHEEL
tabsynth-1.0.6.dist-info/entry_points.txt
tabsynth-1.0.6.dist-info/top_level.txt
tabsynth-1.0.6.dist-info/RECORD
